[
  {
    "id": 1,
    "x": 621,
    "y": 0,
    "width": 41,
    "height": 47,
    "center_x": 642,
    "center_y": 24,
    "relative_x": 0.6265,
    "relative_y": 0.0411,
    "relative_radius": 0.0229
  },
  {
    "id": 2,
    "x": 220,
    "y": 325,
    "width": 175,
    "height": 69,
    "center_x": 308,
    "center_y": 360,
    "relative_x": 0.3003,
    "relative_y": 0.6285,
    "relative_radius": 0.0854
  },
  {
    "id": 3,
    "x": 640,
    "y": 202,
    "width": 190,
    "height": 186,
    "center_x": 735,
    "center_y": 295,
    "relative_x": 0.7178,
    "relative_y": 0.5157,
    "relative_radius": 0.0928
  },
  {
    "id": 4,
    "x": 407,
    "y": 317,
    "width": 98,
    "height": 113,
    "center_x": 456,
    "center_y": 374,
    "relative_x": 0.4453,
    "relative_y": 0.653,
    "relative_radius": 0.0552
  },
  {
    "id": 5,
    "x": 456,
    "y": 52,
    "width": 133,
    "height": 199,
    "center_x": 523,
    "center_y": 152,
    "relative_x": 0.5103,
    "relative_y": 0.2649,
    "relative_radius": 0.0972
  },
  {
    "id": 6,
    "x": 112,
    "y": 2,
    "width": 204,
    "height": 115,
    "center_x": 214,
    "center_y": 60,
    "relative_x": 0.209,
    "relative_y": 0.104,
    "relative_radius": 0.0996
  },
  {
    "id": 7,
    "x": 8,
    "y": 297,
    "width": 59,
    "height": 73,
    "center_x": 38,
    "center_y": 334,
    "relative_x": 0.0366,
    "relative_y": 0.583,
    "relative_radius": 0.0356
  },
  {
    "id": 8,
    "x": 68,
    "y": 250,
    "width": 66,
    "height": 71,
    "center_x": 101,
    "center_y": 286,
    "relative_x": 0.0986,
    "relative_y": 0.4991,
    "relative_radius": 0.0347
  }
]