[
  {
    "id": 1,
    "x": 60,
    "y": 499,
    "width": 44,
    "height": 42,
    "center_x": 82,
    "center_y": 520,
    "relative_x": 0.0801,
    "relative_y": 0.9091,
    "relative_radius": 0.0215
  },
  {
    "id": 2,
    "x": 909,
    "y": 425,
    "width": 53,
    "height": 39,
    "center_x": 936,
    "center_y": 445,
    "relative_x": 0.9136,
    "relative_y": 0.7771,
    "relative_radius": 0.0259
  },
  {
    "id": 3,
    "x": 507,
    "y": 380,
    "width": 40,
    "height": 52,
    "center_x": 527,
    "center_y": 406,
    "relative_x": 0.5146,
    "relative_y": 0.7098,
    "relative_radius": 0.0254
  },
  {
    "id": 4,
    "x": 417,
    "y": 371,
    "width": 63,
    "height": 51,
    "center_x": 449,
    "center_y": 397,
    "relative_x": 0.438,
    "relative_y": 0.6932,
    "relative_radius": 0.0308
  },
  {
    "id": 5,
    "x": 592,
    "y": 51,
    "width": 31,
    "height": 27,
    "center_x": 608,
    "center_y": 65,
    "relative_x": 0.5933,
    "relative_y": 0.1128,
    "relative_radius": 0.0151
  },
  {
    "id": 6,
    "x": 667,
    "y": 39,
    "width": 37,
    "height": 36,
    "center_x": 686,
    "center_y": 57,
    "relative_x": 0.6694,
    "relative_y": 0.0997,
    "relative_radius": 0.0181
  },
  {
    "id": 7,
    "x": 768,
    "y": 36,
    "width": 77,
    "height": 59,
    "center_x": 807,
    "center_y": 66,
    "relative_x": 0.7876,
    "relative_y": 0.1145,
    "relative_radius": 0.0376
  },
  {
    "id": 8,
    "x": 109,
    "y": 26,
    "width": 40,
    "height": 42,
    "center_x": 129,
    "center_y": 47,
    "relative_x": 0.126,
    "relative_y": 0.0822,
    "relative_radius": 0.0205
  },
  {
    "id": 9,
    "x": 877,
    "y": 190,
    "width": 144,
    "height": 97,
    "center_x": 949,
    "center_y": 239,
    "relative_x": 0.9268,
    "relative_y": 0.417,
    "relative_radius": 0.0703
  },
  {
    "id": 10,
    "x": 467,
    "y": 154,
    "width": 33,
    "height": 37,
    "center_x": 484,
    "center_y": 173,
    "relative_x": 0.4722,
    "relative_y": 0.3016,
    "relative_radius": 0.0181
  }
]
